DataIntellect/__init__.py
DataIntellect/flag.py
dataintellect-0.0.0.dist-info/LICENSE
dataintellect-0.0.0.dist-info/METADATA
dataintellect-0.0.0.dist-info/WHEEL
dataintellect-0.0.0.dist-info/top_level.txt
dataintellect-0.0.0.dist-info/RECORD
