Metadata-Version: 2.1
Name: dataintellect
Version: 0.0.0
Summary: Initial package
Author: Data Intellect
Author-email: dataanalytics@dataintellect.com
License-File: LICENSE
